action_triggers/__init__.py
action_triggers/actions/__init__.py
action_triggers/actions/action.py
action_triggers/actions/aws/__init__.py
action_triggers/actions/aws/aws_lambda.py
action_triggers/actions/enums.py
action_triggers/actions/error.py
action_triggers/admin.py
action_triggers/api/__init__.py
action_triggers/api/serializers.py
action_triggers/api/urls.py
action_triggers/api/views.py
action_triggers/apps.py
action_triggers/base/__init__.py
action_triggers/base/config.py
action_triggers/base/error.py
action_triggers/checks.py
action_triggers/conf.py
action_triggers/config_required_fields.py
action_triggers/core/__init__.py
action_triggers/core/config.py
action_triggers/descriptors/__init__.py
action_triggers/descriptors/config_field.py
action_triggers/descriptors/error.py
action_triggers/dispatch.py
action_triggers/dynamic_loading.py
action_triggers/enums.py
action_triggers/exceptions.py
action_triggers/message_broker/__init__.py
action_triggers/message_broker/aws_sns.py
action_triggers/message_broker/aws_sqs.py
action_triggers/message_broker/broker.py
action_triggers/message_broker/enums.py
action_triggers/message_broker/error.py
action_triggers/message_broker/gcp_pubsub.py
action_triggers/message_broker/kafka.py
action_triggers/message_broker/queue.py
action_triggers/message_broker/rabbitmq.py
action_triggers/message_broker/redis.py
action_triggers/migrations/0001_initial.py
action_triggers/migrations/0002_rename_models_config_content_types_config_active.py
action_triggers/migrations/0003_rename_config_id_configsignal_config.py
action_triggers/migrations/0004_rename_config_id_messagebrokerqueue_config_and_more.py
action_triggers/migrations/0005_messagebrokerqueue_conn_details.py
action_triggers/migrations/0006_alter_config_content_types.py
action_triggers/migrations/0007_messagebrokerqueue_timeout_secs_webhook_timeout_secs.py
action_triggers/migrations/0008_action.py
action_triggers/migrations/__init__.py
action_triggers/models.py
django_action_triggers-0.5.2.dist-info/LICENSE
django_action_triggers-0.5.2.dist-info/METADATA
django_action_triggers-0.5.2.dist-info/WHEEL
django_action_triggers-0.5.2.dist-info/RECORD
