Metadata-Version: 2.1
Name: django-action-triggers
Version: 0.5.2
Summary: A Django library for asynchronously triggering actions in response to database changes. It supports integration with webhooks, message brokers (e.g., Kafka, RabbitMQ), and can trigger other processes, including AWS Lambda functions.
Home-page: https://github.com/Salaah01/django-action-triggers
License: MIT
Keywords: django,signals,actions,triggers,webhooks,kafka,rabbitmq,async,asyncio,aiohttp,aiokafka,aio-pika,message-broker,message-queue,message-bus,pubsub,event-driven,event-driven
Author: Salaah Amin
Author-email: salaah01@users.noreply.github.com
Requires-Python: >=3.8,<3.13
Classifier: Development Status :: 5 - Production/Stable
Classifier: Environment :: Web Environment
Classifier: Framework :: Django
Classifier: Framework :: Django :: 3.2
Classifier: Framework :: Django :: 4.2
Classifier: Framework :: Django :: 5.0
Classifier: Framework :: Django :: 5.1
Classifier: Intended Audience :: Developers
Classifier: License :: OSI Approved :: MIT License
Classifier: Programming Language :: Python
Classifier: Programming Language :: Python :: 3
Classifier: Programming Language :: Python :: 3.8
Classifier: Programming Language :: Python :: 3.9
Classifier: Programming Language :: Python :: 3.10
Classifier: Programming Language :: Python :: 3.11
Classifier: Programming Language :: Python :: 3.12
Provides-Extra: aws
Provides-Extra: gcp
Provides-Extra: kafka
Provides-Extra: postgres
Provides-Extra: rabbitmq
Provides-Extra: redis
Provides-Extra: webhooks
Requires-Dist: aio-pika (>=9.4.3,<10.0.0) ; extra == "rabbitmq"
Requires-Dist: aiohttp (>=3.10.5,<4.0.0) ; extra == "webhooks"
Requires-Dist: aiokafka (>=0.11.0,<0.12.0) ; extra == "kafka"
Requires-Dist: boto3 (>=1.35.12,<2.0.0) ; extra == "aws"
Requires-Dist: django (>=3.2,<5.1)
Requires-Dist: djangorestframework (>=3.0.0,<3.15.2)
Requires-Dist: google-cloud-pubsub (>=2.25.2,<3.0.0) ; extra == "gcp"
Requires-Dist: psycopg2 (>=2.9.9,<3.0.0) ; extra == "postgres"
Requires-Dist: redis (>=5.0.8,<6.0.0) ; extra == "redis"
Project-URL: Documentation, https://django-action-triggers.readthedocs.io/en/latest/
Project-URL: Repository, https://github.com/Salaah01/django-action-triggers
